magicalapi/__init__.py
magicalapi/client.py
magicalapi/errors.py
magicalapi/settings.py
magicalapi/abstractions/__init__.py
magicalapi/abstractions/base_service.py
magicalapi/services/__init__.py
magicalapi/services/base_service.py
magicalapi/services/company_data_service.py
magicalapi/services/profile_data_service.py
magicalapi/services/resume_parser_service.py
magicalapi/services/resume_review_service.py
magicalapi/services/resume_score_service.py
magicalapi/types/__init__.py
magicalapi/types/base.py
magicalapi/types/company_data.py
magicalapi/types/profile_data.py
magicalapi/types/resume_parser.py
magicalapi/types/resume_review.py
magicalapi/types/resume_score.py
magicalapi/types/schemas.py
magicalapi/utils/logger.py
magicalapi-1.5.1.dist-info/METADATA
magicalapi-1.5.1.dist-info/WHEEL
magicalapi-1.5.1.dist-info/licenses/LICENSE
magicalapi-1.5.1.dist-info/RECORD
